adamic/__init__.py
adamic/adamic.py
adamic-0.1.3.dist-info/LICENSE.txt
adamic-0.1.3.dist-info/METADATA
adamic-0.1.3.dist-info/WHEEL
adamic-0.1.3.dist-info/top_level.txt
adamic-0.1.3.dist-info/RECORD
