Metadata-Version: 2.1
Name: adamic
Version: 0.1.3
Summary: A package to create data dictionaries, given a Pandas df
Home-page: https://github.com/redsoxfan0219/adamic
Author: Ben Moran
Author-email: benjamin.moran.287@gmail.com
License: MIT License
Project-URL: Bug Tracker, https://github.com/redsoxfan0219/adamic/issues
Platform: UNKNOWN
Classifier: Programming Language :: Python :: 3
Classifier: License :: OSI Approved :: MIT License
Classifier: Operating System :: OS Independent
Requires-Python: >=3.6
Requires-Dist: pandas (>=1.1)
